discord_to_postgresql/__init__.py
discord_to_postgresql/__main__.py
discord_to_postgresql/load.py
discord_to_postgresql/run.py
discord_to_postgresql/transform.py
discord_to_postgresql-0.1.2.dist-info/LICENSE.md
discord_to_postgresql-0.1.2.dist-info/METADATA
discord_to_postgresql-0.1.2.dist-info/WHEEL
discord_to_postgresql-0.1.2.dist-info/entry_points.txt
discord_to_postgresql-0.1.2.dist-info/top_level.txt
discord_to_postgresql-0.1.2.dist-info/RECORD
