Metadata-Version: 2.1
Name: discord-to-postgresql
Version: 0.1.2
Summary: Imports Discord messages archive to PostgreSQL database
Home-page: https://github.com/carlaraya/discord-to-postgresql
Author: Carl Araya
License: Apache License 2.0
Classifier: Programming Language :: Python :: 3
License-File: LICENSE.md
Requires-Dist: fire
Requires-Dist: numpy
Requires-Dist: pandas
Requires-Dist: sqlalchemy
Requires-Dist: psycopg2-binary
